blockchain/__init__.py
blockchain/block.py
estudos_blockchain-1.0.dist-info/METADATA
estudos_blockchain-1.0.dist-info/WHEEL
estudos_blockchain-1.0.dist-info/top_level.txt
estudos_blockchain-1.0.dist-info/RECORD
