Metadata-Version: 2.1
Name: estudos-blockchain
Version: 1.0
Summary: Estudos simples sobre blockchain
Home-page: https://github.com/sostenes198/Python-Estudos
Author: Sóstenes Gonçalves
Author-email: sostenes198br@hotmail.com
License: MIT
Platform: UNKNOWN
